apimaticcalculator/__init__.py
apimaticcalculator/api_helper.py
apimaticcalculator/apimaticcalculator_client.py
apimaticcalculator/configuration.py
apimaticcalculator/apis/__init__.py
apimaticcalculator/apis/base_api.py
apimaticcalculator/apis/simple_calculator_api.py
apimaticcalculator/exceptions/__init__.py
apimaticcalculator/exceptions/api_exception.py
apimaticcalculator/http/__init__.py
apimaticcalculator/http/api_response.py
apimaticcalculator/http/http_call_back.py
apimaticcalculator/http/http_client_provider.py
apimaticcalculator/http/http_method_enum.py
apimaticcalculator/http/http_request.py
apimaticcalculator/http/http_response.py
apimaticcalculator/http/proxy_settings.py
apimaticcalculator/logging/__init__.py
apimaticcalculator/logging/sdk_logger.py
apimaticcalculator/logging/configuration/__init__.py
apimaticcalculator/logging/configuration/api_logging_configuration.py
apimaticcalculator/models/__init__.py
apimaticcalculator/models/operation_type.py
apimaticcalculator/utilities/__init__.py
apimaticcalculator/utilities/file_wrapper.py
calc_matic-1.0.0.dist-info/licenses/LICENSE
calc_matic-1.0.0.dist-info/METADATA
calc_matic-1.0.0.dist-info/WHEEL
calc_matic-1.0.0.dist-info/top_level.txt
calc_matic-1.0.0.dist-info/RECORD
